{
  "rootKey": "graph-analyzer_work.js",
  "graph": {
    "__filename": [],
    "__dirname": [
      "__filename"
    ],
    "IGNORE_NODE_MODULES": [],
    "SUPPORTED_EXTENSIONS": [],
    "VUE_SCRIPT_PATTERN": [],
    "parseFile": [
      "VUE_SCRIPT_PATTERN"
    ],
    "isExternalModule": [],
    "resolveFilePath": [
      "SUPPORTED_EXTENSIONS"
    ],
    "getAllProjectFiles": [
      "SUPPORTED_EXTENSIONS"
    ],
    "minifyCodeString": [],
    "minifyForAI": [
      "parseFile",
      "minifyCodeString"
    ],
    "buildProjectGraph": [
      "parseFile",
      "IGNORE_NODE_MODULES",
      "isExternalModule",
      "resolveFilePath"
    ],
    "buildFileInternalGraph": [
      "parseFile"
    ],
    "buildAiPromptPack": [
      "buildProjectGraph",
      "minifyForAI"
    ],
    "runImpactAnalysis": [
      "getAllProjectFiles",
      "parseFile",
      "resolveFilePath"
    ],
    "findDeadCode": [
      "parseFile",
      "getAllProjectFiles",
      "resolveFilePath"
    ],
    "findCyclicEdges": [],
    "convertToDOT": [],
    "generateHTMLReport": [
      "escapeHtml"
    ],
    "escapeHtml": [],
    "main": [
      "findDeadCode",
      "runImpactAnalysis",
      "buildAiPromptPack",
      "minifyForAI",
      "buildFileInternalGraph",
      "buildProjectGraph",
      "findCyclicEdges",
      "convertToDOT",
      "generateHTMLReport"
    ]
  },
  "hasCycles": false,
  "cyclicEdges": []
}